pixel_core/__init__.py
pixel_core/filters.py
pixel_core/image_utils.py
scorpia_pixel-0.1.0.dist-info/licenses/LICENSE
scorpia_pixel-0.1.0.dist-info/METADATA
scorpia_pixel-0.1.0.dist-info/WHEEL
scorpia_pixel-0.1.0.dist-info/top_level.txt
scorpia_pixel-0.1.0.dist-info/RECORD
