Metadata-Version: 2.4
Name: scorpia-pixel
Version: 0.1.0
Summary: A lightweight Python package for learning image processing by building filters from scratch
Author-email: Montasar Dridi <you@example.com>
License-Expression: MIT
Project-URL: Homepage, https://github.com/Montasar-Dridi/scorpia-pixel
Project-URL: Repository, https://github.com/Montasar-Dridi/scorpia-pixel
Requires-Python: >=3.8
License-File: LICENSE
Requires-Dist: numpy
Requires-Dist: pillow
Dynamic: license-file
